Combitional Circuits/FourBitAdderSubractor/HalfAdder.v
module HalfAdder(Sum, Carry, A, B);
    output Sum, Carry;
    input A, B;
    assign Sum = A ^ B;
    assign Carry = A & B;
endmodule

Combitional Circuits/FourBitParallelAdder/FullAdder.v
module FullAdder (Sum, Carry, A, B, Cin);
    output Sum, Carry;
    input A, B, Cin;
    wire w1, w2, w3;

    HalfAdder A1(.Sum(w1), .Carry(w2), .A(A), .B(B));
    HalfAdder A2(.Sum(Sum), .Carry(w3), .A(w1), .B(Cin));
    assign Carry = w2 | w3;
endmodule

Combitional Circuits/FourBitAdderSubractor/FourBitAdderSubractor.v
module FourBitAdderSubractor (Sum, Carry, A, B, Sel);
    output [3:0]Sum;
    output Carry;
    input [3:0]A, B;
    input Sel;
    wire [2:0]w;
    wire [3:0]i;

    assign i = B ^ {4{Sel}};
    FullAdder A0(.Sum(Sum[0]), .Carry(w[0]), .A(A[0]), .B(i[0]), .Cin(Sel));
    FullAdder A1(.Sum(Sum[1]), .Carry(w[1]), .A(A[1]), .B(i[1]), .Cin(w[0]));
    FullAdder A2(.Sum(Sum[2]), .Carry(w[2]), .A(A[2]), .B(i[2]), .Cin(w[1]));
    FullAdder A3(.Sum(Sum[3]), .Carry(Carry), .A(A[3]), .B(i[3]), .Cin(w[2]));
    

endmodule

Combitional Circuits/FourBitAdderSubractor/tb.sv
module tb;
    reg [3:0]A, B;
    reg Sel;
    wire [3:0]Sum;
    wire Carry;


    FourBitAdderSubractor dut(.Sum(Sum), .Carry(Carry), .A(A), .B(B), .Sel(Sel));
    integer i;
    reg [4:0]Addition, Subraction;
    
    initial begin 
        $dumpfile("ww.vcd");
        $dumpvars(0, tb);
        for (i = 0; i<512; i++) begin
            {A, B, Sel} = i;
            Addition = A + B + Sel;
            Subraction = A - B;
            #10;
            if(Sel == 0 & Addition[3:0] == Sum & Addition[4] == Carry) 
                $display("pased coz A=%0d B=%0d Sel=%b Sum=%0d Carry=%b & Addition=%0d Subraction=%0d", A, B, Sel, Sum, Carry, Addition, Subraction);
            else if(Sel == 1 & Subraction[3:0] == Sum & Subraction[4] == ~Carry) 
                $display("pased coz A=%0d B=%0d Sel=%b Sum=%0d Carry=%b & Addition=%0d Subraction=%0d", A, B, Sel, Sum, Carry, Addition, Subraction);
            else begin
                $display("failed coz A=%0d B=%0d Sel=%b Sum=%0d Carry=%b & Addition=%0d Subraction=%0d", A, B, Sel, Sum, Carry, Addition, Subraction);
                $finish();
            end
        end
    end

endmodule

Combitional Circuits/FourBitAdderSubractor/ww.vcd
$date
	Mon Aug 23 19:40:14 2021
$end
$version
	Icarus Verilog
$end
$timescale
	1s
$end
$scope module tb $end
$var wire 4 ! Sum [3:0] $end
$var wire 1 " Carry $end
$var reg 4 # A [3:0] $end
$var reg 5 $ Addition [4:0] $end
$var reg 4 % B [3:0] $end
$var reg 1 & Sel $end
$var reg 5 ' Subraction [4:0] $end
$var integer 32 ( i [31:0] $end
$scope module dut $end
$var wire 4 ) A [3:0] $end
$var wire 4 * B [3:0] $end
$var wire 1 & Sel $end
$var wire 4 + i [3:0] $end
$var wire 3 , w [2:0] $end
$var wire 4 - Sum [3:0] $end
$var wire 1 " Carry $end
$scope module A0 $end
$var wire 1 . A $end
$var wire 1 / B $end
$var wire 1 0 Carry $end
$var wire 1 & Cin $end
$var wire 1 1 w3 $end
$var wire 1 2 w2 $end
$var wire 1 3 w1 $end
$var wire 1 4 Sum $end
$scope module A1 $end
$var wire 1 . A $end
$var wire 1 / B $end
$var wire 1 2 Carry $end
$var wire 1 3 Sum $end
$upscope $end
$scope module A2 $end
$var wire 1 3 A $end
$var wire 1 & B $end
$var wire 1 1 Carry $end
$var wire 1 4 Sum $end
$upscope $end
$upscope $end
$scope module A1 $end
$var wire 1 5 A $end
$var wire 1 6 B $end
$var wire 1 7 Carry $end
$var wire 1 8 Cin $end
$var wire 1 9 w3 $end
$var wire 1 : w2 $end
$var wire 1 ; w1 $end
$var wire 1 < Sum $end
$scope module A1 $end
$var wire 1 5 A $end
$var wire 1 6 B $end
$var wire 1 : Carry $end
$var wire 1 ; Sum $end
$upscope $end
$scope module A2 $end
$var wire 1 ; A $end
$var wire 1 8 B $end
$var wire 1 9 Carry $end
$var wire 1 < Sum $end
$upscope $end
$upscope $end
$scope module A2 $end
$var wire 1 = A $end
$var wire 1 > B $end
$var wire 1 ? Carry $end
$var wire 1 @ Cin $end
$var wire 1 A w3 $end
$var wire 1 B w2 $end
$var wire 1 C w1 $end
$var wire 1 D Sum $end
$scope module A1 $end
$var wire 1 = A $end
$var wire 1 > B $end
$var wire 1 B Carry $end
$var wire 1 C Sum $end
$upscope $end
$scope module A2 $end
$var wire 1 C A $end
$var wire 1 @ B $end
$var wire 1 A Carry $end
$var wire 1 D Sum $end
$upscope $end
$upscope $end
$scope module A3 $end
$var wire 1 E A $end
$var wire 1 F B $end
$var wire 1 " Carry $end
$var wire 1 G Cin $end
$var wire 1 H w3 $end
$var wire 1 I w2 $end
$var wire 1 J w1 $end
$var wire 1 K Sum $end
$scope module A1 $end
$var wire 1 E A $end
$var wire 1 F B $end
$var wire 1 I Carry $end
$var wire 1 J Sum $end
$upscope $end
$scope module A2 $end
$var wire 1 J A $end
$var wire 1 G B $end
$var wire 1 H Carry $end
$var wire 1 K Sum $end
$upscope $end
$upscope $end
$upscope $end
$upscope $end
$enddefinitions $end
#0
$dumpvars
0K
0J
0I
0H
0G
0F
0E
0D
0C
0B
0A
0@
0?
0>
0=
0<
0;
0:
09
08
07
06
05
04
03
02
01
00
0/
0.
b0 -
b0 ,
b0 +
b0 *
b0 )
b0 (
b0 '
0&
b0 %
b0 $
b0 #
0"
b0 !
$end
#10
1"
1H
1G
1?
1A
1@
17
19
18
b111 ,
10
11
0<
0D
0K
13
1;
1C
1J
1/
16
1>
1F
b1111 +
b0 !
b0 -
04
b1 $
1&
b1 (
#20
0G
0@
0?
0"
07
0D
0A
0K
0H
09
0;
0C
0J
08
06
0>
0F
b0 ,
00
b1 +
b1 !
b1 -
14
01
b11111 '
b1 %
b1 *
0&
b10 (
#30
0"
0H
0G
0?
1<
0A
0@
07
1D
1K
09
03
1;
1C
1J
08
0/
16
1>
1F
b0 ,
00
b1110 +
b1111 !
b1111 -
14
01
b10 $
1&
b11 (
#40
0D
0K
0C
0J
0>
0F
b10 +
b10 !
b10 -
04
b11110 '
b10 %
b10 *
0&
b100 (
#50
18
b1 ,
10
11
1<
1D
1K
13
0;
1C
1J
1/
06
1>
1F
b1101 +
b1110 !
b1110 -
04
b11 $
1&
b101 (
#60
0D
0K
1;
0C
0J
08
16
0>
0F
b0 ,
00
b11 +
b11 !
b11 -
14
01
b11101 '
b11 %
b11 *
0&
b110 (
#70
0<
1D
1K
03
0;
1C
1J
08
0/
06
1>
1F
b0 ,
00
b1100 +
b1101 !
b1101 -
14
01
b100 $
1&
b111 (
#80
0K
0J
0F
b100 +
b100 !
b100 -
04
b11100 '
b100 %
b100 *
0&
b1000 (
#90
1@
17
19
18
b11 ,
10
11
0<
1D
1K
13
1;
0C
1J
1/
16
0>
1F
b1011 +
b1100 !
b1100 -
04
b101 $
1&
b1001 (
#100
0G
0@
0?
07
1D
0A
0K
09
0;
1C
0J
08
06
1>
0F
b0 ,
00
b101 +
b101 !
b101 -
14
01
b11011 '
b101 %
b101 *
0&
b1010 (
#110
1<
0@
07
0D
1K
09
03
1;
0C
1J
08
0/
16
0>
1F
b0 ,
00
b1010 +
b1011 !
b1011 -
14
01
b110 $
1&
b1011 (
#120
1D
0K
1C
0J
1>
0F
b110 +
b110 !
b110 -
04
b11010 '
b110 %
b110 *
0&
b1100 (
#130
18
b1 ,
10
11
1<
0D
1K
13
0;
0C
1J
1/
06
0>
1F
b1001 +
b1010 !
b1010 -
04
b111 $
1&
b1101 (
#140
1D
0K
1;
1C
0J
08
16
1>
0F
b0 ,
00
b111 +
b111 !
b111 -
14
01
b11001 '
b111 %
b111 *
0&
b1110 (
#150
0<
0D
1K
03
0;
0C
1J
08
0/
06
0>
1F
b0 ,
00
b1000 +
b1001 !
b1001 -
14
01
b1000 $
1&
b1111 (
#160
b1000 !
b1000 -
04
b11000 '
b1000 %
b1000 *
0&
b10000 (
#170
1G
1?
1A
1@
17
19
18
b111 ,
10
11
0<
0D
1K
13
1;
1C
0J
1/
16
1>
0F
b111 +
b1000 !
b1000 -
04
b1001 $
1&
b10001 (
#180
0G
0@
0?
0"
07
0D
0A
1K
0H
09
0;
0C
1J
08
06
0>
1F
b0 ,
00
b1001 +
b1001 !
b1001 -
14
01
b10111 '
b1001 %
b1001 *
0&
b10010 (
#190
0G
0?
1<
0A
0@
07
1D
0K
09
03
1;
1C
0J
08
0/
16
1>
0F
b0 ,
00
b110 +
b111 !
b111 -
14
01
b1010 $
1&
b10011 (
#200
0D
1K
0C
1J
0>
1F
b1010 +
b1010 !
b1010 -
04
b10110 '
b1010 %
b1010 *
0&
b10100 (
#210
18
b1 ,
10
11
1<
1D
0K
13
0;
1C
0J
1/
06
1>
0F
b101 +
b110 !
b110 -
04
b1011 $
1&
b10101 (
#220
0D
1K
1;
0C
1J
08
16
0>
1F
b0 ,
00
b1011 +
b1011 !
b1011 -
14
01
b10101 '
b1011 %
b1011 *
0&
b10110 (
#230
0<
1D
0K
03
0;
1C
0J
08
0/
06
1>
0F
b0 ,
00
b100 +
b101 !
b101 -
14
01
b1100 $
1&
b10111 (
#240
1K
1J
1F
b1100 +
b1100 !
b1100 -
04
b10100 '
b1100 %
b1100 *
0&
b11000 (
#250
1@
17
19
18
b11 ,
10
11
0<
1D
0K
13
1;
0C
0J
1/
16
0>
0F
b11 +
b100 !
b100 -
04
b1101 $
1&
b11001 (
#260
0"
0H
0G
0@
0?
07
1D
0A
1K
09
0;
1C
1J
08
06
1>
1F
b0 ,
00
b1101 +
b1101 !
b1101 -
14
01
b10011 '
b1101 %
b1101 *
0&
b11010 (
#270
1<
0@
07
0D
0K
09
03
1;
0C
0J
08
0/
16
0>
0F
b0 ,
00
b10 +
b11 !
b11 -
14
01
b1110 $
1&
b11011 (
#280
1D
1K
1C
1J
1>
1F
b1110 +
b1110 !
b1110 -
04
b10010 '
b1110 %
b1110 *
0&
b11100 (
#290
18
b1 ,
10
11
1<
0D
0K
13
0;
0C
0J
1/
06
0>
0F
b1 +
b10 !
b10 -
04
b1111 $
1&
b11101 (
#300
1D
1K
1;
1C
1J
08
16
1>
1F
b0 ,
00
b1111 +
b1111 !
b1111 -
14
01
b10001 '
b1111 %
b1111 *
0&
b11110 (
#310
0<
0D
0K
03
0;
0C
0J
08
0/
06
0>
0F
b0 ,
00
b0 +
b1 !
b1 -
14
01
b10000 $
1&
b11111 (
#320
13
1.
b1 !
b1 -
14
b1 '
b1 $
b1 #
b1 )
b0 %
b0 *
0&
b100000 (
#330
1"
1H
1G
1?
1A
1@
17
0D
0K
19
03
12
1;
1C
1J
18
1/
16
1>
1F
b111 ,
10
b1111 +
b1 !
b1 -
14
01
b10 $
1&
b100001 (
#340
0@
0G
07
b1 ,
0?
0"
1<
09
0D
0A
0K
0H
0;
0C
0J
06
0>
0F
b1 +
b10 !
b10 -
04
b0 '
b1 %
b1 *
0&
b100010 (
#350
1"
1H
1G
1?
1A
1@
18
17
11
b111 ,
10
0<
19
0D
0K
13
02
1;
1C
1J
0/
16
1>
1F
b1110 +
b0 !
b0 -
04
b11 $
1&
b100011 (
#360
0G
0@
0?
0"
07
0D
0A
0K
0H
1<
09
0C
0J
08
0>
0F
b0 ,
00
b10 +
b11 !
b11 -
14
01
b11111 '
b10 %
b10 *
0&
b100100 (
#370
1D
1K
03
12
0;
1C
1J
18
1/
06
1>
1F
b1 ,
10
b1101 +
b1111 !
b1111 -
14
01
b100 $
1&
b100101 (
#380
1@
b11 ,
17
0<
19
1D
0K
1;
0C
0J
16
0>
0F
b11 +
b100 !
b100 -
04
b11110 '
b11 %
b11 *
0&
b100110 (
#390
0"
0H
0@
0G
18
07
0?
11
b1 ,
10
1<
09
1D
0A
1K
13
02
0;
1C
1J
0/
06
1>
1F
b1100 +
b1110 !
b1110 -
04
b101 $
1&
b100111 (
#400
0K
0<
0J
08
0F
b0 ,
00
b100 +
b101 !
b101 -
14
01
b11101 '
b100 %
b100 *
0&
b101000 (
#410
1@
17
1D
1K
19
03
12
1;
0C
1J
18
1/
16
0>
1F
b11 ,
10
b1011 +
b1101 !
b1101 -
14
01
b110 $
1&
b101001 (
#420
0@
0G
07
b1 ,
0?
1<
09
1D
0A
0K
0;
1C
0J
06
1>
0F
b101 +
b110 !
b110 -
04
b11100 '
b101 %
b101 *
0&
b101010 (
#430
1@
18
17
11
b11 ,
10
0<
19
1D
1K
13
02
1;
0C
1J
0/
16
0>
1F
b1010 +
b1100 !
b1100 -
04
b111 $
1&
b101011 (
#440
0G
0@
0?
07
1D
0A
0K
1<
09
1C
0J
08
1>
0F
b0 ,
00
b110 +
b111 !
b111 -
14
01
b11011 '
b110 %
b110 *
0&
b101100 (
#450
0D
1K
03
12
0;
0C
1J
18
1/
06
0>
1F
b1 ,
10
b1001 +
b1011 !
b1011 -
14
01
b1000 $
1&
b101101 (
#460
1G
1?
1A
1@
b111 ,
17
0<
19
0D
1K
1;
1C
0J
16
1>
0F
b111 +
b1000 !
b1000 -
04
b11010 '
b111 %
b111 *
0&
b101110 (
#470
0@
0G
18
07
0?
0"
11
b1 ,
10
1<
09
0D
0A
1K
0H
13
02
0;
0C
1J
0/
06
0>
1F
b1000 +
b1010 !
b1010 -
04
b1001 $
1&
b101111 (
#480
0<
08
b0 ,
00
b1001 !
b1001 -
14
01
b11001 '
b1000 %
b1000 *
0&
b110000 (
#490
1G
1?
1A
1@
17
0D
1K
19
03
12
1;
1C
0J
18
1/
16
1>
0F
b111 ,
10
b111 +
b1001 !
b1001 -
14
01
b1010 $
1&
b110001 (
#500
0@
0G
07
b1 ,
0?
0"
1<
09
0D
0A
1K
0H
0;
0C
1J
06
0>
1F
b1001 +
b1010 !
b1010 -
04
b11000 '
b1001 %
b1001 *
0&
b110010 (
#510
1G
1?
1A
1@
18
17
11
b111 ,
10
0<
19
0D
1K
13
02
1;
1C
0J
0/
16
1>
0F
b110 +
b1000 !
b1000 -
04
b1011 $
1&
b110011 (
#520
0G
0@
0?
0"
07
0D
0A
1K
0H
1<
09
0C
1J
08
0>
1F
b0 ,
00
b1010 +
b1011 !
b1011 -
14
01
b10111 '
b1010 %
b1010 *
0&
b110100 (
#530
1D
0K
03
12
0;
1C
0J
18
1/
06
1>
0F
b1 ,
10
b101 +
b111 !
b111 -
14
01
b1100 $
1&
b110101 (
#540
1@
b11 ,
17
0<
19
1D
1K
1;
0C
1J
16
0>
1F
b1011 +
b1100 !
b1100 -
04
b10110 '
b1011 %
b1011 *
0&
b110110 (
#550
0@
0G
18
07
0?
11
b1 ,
10
1<
09
1D
0A
0K
13
02
0;
1C
0J
0/
06
1>
0F
b100 +
b110 !
b110 -
04
b1101 $
1&
b110111 (
#560
1K
0<
1J
08
1F
b0 ,
00
b1100 +
b1101 !
b1101 -
14
01
b10101 '
b1100 %
b1100 *
0&
b111000 (
#570
1@
17
1D
0K
19
03
12
1;
0C
0J
18
1/
16
0>
0F
b11 ,
10
b11 +
b101 !
b101 -
14
01
b1110 $
1&
b111001 (
#580
0"
0H
0@
0G
07
b1 ,
0?
1<
09
1D
0A
1K
0;
1C
1J
06
1>
1F
b1101 +
b1110 !
b1110 -
04
b10100 '
b1101 %
b1101 *
0&
b111010 (
#590
1@
18
17
11
b11 ,
10
0<
19
1D
0K
13
02
1;
0C
0J
0/
16
0>
0F
b10 +
b100 !
b100 -
04
b1111 $
1&
b111011 (
#600
0"
0H
0G
0@
0?
07
1D
0A
1K
1<
09
1C
1J
08
1>
1F
b0 ,
00
b1110 +
b1111 !
b1111 -
14
01
b10011 '
b1110 %
b1110 *
0&
b111100 (
#610
0D
0K
03
12
0;
0C
0J
18
1/
06
0>
0F
b1 ,
10
b1 +
b11 !
b11 -
14
01
b10000 $
1&
b111101 (
#620
1"
1H
1G
1?
1A
1@
b111 ,
17
0<
19
0D
0K
1;
1C
1J
16
1>
1F
b1111 +
b0 !
b0 -
04
b10010 '
b1111 %
b1111 *
0&
b111110 (
#630
0@
0G
18
07
0?
0"
11
b1 ,
10
1<
09
0D
0A
0K
0H
13
02
0;
0C
0J
0/
06
0>
0F
b0 +
b10 !
b10 -
04
b10001 $
1&
b111111 (
#640
08
03
1;
b0 ,
00
0.
15
b10 !
b10 -
04
01
b10 '
b10 $
b10 #
b10 )
b0 %
b0 *
0&
b1000000 (
#650
1"
1H
1G
1?
18
1A
10
1@
11
1<
b111 ,
17
0D
0K
13
0;
1:
1C
1J
1/
16
1>
1F
b1111 +
b10 !
b10 -
04
b11 $
1&
b1000001 (
#660
0G
0@
0?
0"
07
0D
0A
0K
0H
1;
0:
0C
0J
08
06
0>
0F
b0 ,
00
b1 +
b11 !
b11 -
14
01
b1 '
b1 %
b1 *
0&
b1000010 (
#670
1"
1H
1G
0<
1?
1A
1@
17
0D
0K
03
0;
1:
1C
1J
08
0/
16
1>
1F
b110 ,
00
b1110 +
b1 !
b1 -
14
01
b100 $
1&
b1000011 (
#680
0G
b10 ,
0?
0"
1D
0A
0K
0H
0C
0J
0>
0F
b10 +
b100 !
b100 -
04
b0 '
b10 %
b10 *
0&
b1000100 (
#690
1"
19
1H
18
1G
10
1@
1?
11
0<
b111 ,
17
0D
1A
0K
13
1;
0:
1C
1J
1/
06
1>
1F
b1101 +
b0 !
b0 -
04
b101 $
1&
b1000101 (
#700
0G
0?
0"
1D
0A
0K
0H
09
0;
1:
0C
0J
08
16
0>
0F
b10 ,
00
b11 +
b101 !
b101 -
14
01
b11111 '
b11 %
b11 *
0&
b1000110 (
#710
0@
07
0"
1<
0H
0G
0?
1D
0A
1K
09
03
1;
0:
1C
1J
08
0/
06
1>
1F
b0 ,
00
b1100 +
b1111 !
b1111 -
14
01
b110 $
1&
b1000111 (
#720
0K
0J
0F
b100 +
b110 !
b110 -
04
b11110 '
b100 %
b100 *
0&
b1001000 (
#730
18
10
1@
11
1<
b11 ,
17
1D
1K
13
0;
1:
0C
1J
1/
16
0>
1F
b1011 +
b1110 !
b1110 -
04
b111 $
1&
b1001001 (
#740
0G
0@
0?
07
1D
0A
0K
1;
0:
1C
0J
08
06
1>
0F
b0 ,
00
b101 +
b111 !
b111 -
14
01
b11101 '
b101 %
b101 *
0&
b1001010 (
#750
0<
1@
17
1D
1K
03
0;
1:
0C
1J
08
0/
16
0>
1F
b10 ,
00
b1010 +
b1101 !
b1101 -
14
01
b1000 $
1&
b1001011 (
#760
1G
b110 ,
1?
0D
1A
1K
1C
0J
1>
0F
b110 +
b1000 !
b1000 -
04
b11100 '
b110 %
b110 *
0&
b1001100 (
#770
19
18
0G
10
1@
0?
0"
11
0<
b11 ,
17
1D
0A
1K
0H
13
1;
0:
0C
1J
1/
06
0>
1F
b1001 +
b1100 !
b1100 -
04
b1001 $
1&
b1001101 (
#780
1G
1?
0D
1A
1K
09
0;
1:
1C
0J
08
16
1>
0F
b110 ,
00
b111 +
b1001 !
b1001 -
14
01
b11011 '
b111 %
b111 *
0&
b1001110 (
#790
0@
07
1<
0G
0?
0"
0D
0A
1K
0H
09
03
1;
0:
0C
1J
08
0/
06
0>
1F
b0 ,
00
b1000 +
b1011 !
b1011 -
14
01
b1010 $
1&
b1001111 (
#800
b1010 !
b1010 -
04
b11010 '
b1000 %
b1000 *
0&
b1010000 (
#810
1G
1?
18
1A
10
1@
11
1<
b111 ,
17
0D
1K
13
0;
1:
1C
0J
1/
16
1>
0F
b111 +
b1010 !
b1010 -
04
b1011 $
1&
b1010001 (
#820
0G
0@
0?
0"
07
0D
0A
1K
0H
1;
0:
0C
1J
08
06
0>
1F
b0 ,
00
b1001 +
b1011 !
b1011 -
14
01
b11001 '
b1001 %
b1001 *
0&
b1010010 (
#830
1G
0<
1?
1A
1@
17
0D
1K
03
0;
1:
1C
0J
08
0/
16
1>
0F
b110 ,
00
b110 +
b1001 !
b1001 -
14
01
b1100 $
1&
b1010011 (
#840
0G
b10 ,
0?
0"
1D
0A
1K
0H
0C
1J
0>
1F
b1010 +
b1100 !
b1100 -
04
b11000 '
b1010 %
b1010 *
0&
b1010100 (
#850
19
18
1G
10
1@
1?
11
0<
b111 ,
17
0D
1A
1K
13
1;
0:
1C
0J
1/
06
1>
0F
b101 +
b1000 !
b1000 -
04
b1101 $
1&
b1010101 (
#860
0G
0?
0"
1D
0A
1K
0H
09
0;
1:
0C
1J
08
16
0>
1F
b10 ,
00
b1011 +
b1101 !
b1101 -
14
01
b10111 '
b1011 %
b1011 *
0&
b1010110 (
#870
0@
07
1<
0G
0?
1D
0A
0K
09
03
1;
0:
1C
0J
08
0/
06
1>
0F
b0 ,
00
b100 +
b111 !
b111 -
14
01
b1110 $
1&
b1010111 (
#880
1K
1J
1F
b1100 +
b1110 !
b1110 -
04
b10110 '
b1100 %
b1100 *
0&
b1011000 (
#890
18
10
1@
11
1<
b11 ,
17
1D
0K
13
0;
1:
0C
0J
1/
16
0>
0F
b11 +
b110 !
b110 -
04
b1111 $
1&
b1011001 (
#900
0"
0H
0G
0@
0?
07
1D
0A
1K
1;
0:
1C
1J
08
06
1>
1F
b0 ,
00
b1101 +
b1111 !
b1111 -
14
01
b10101 '
b1101 %
b1101 *
0&
b1011010 (
#910
0<
1@
17
1D
0K
03
0;
1:
0C
0J
08
0/
16
0>
0F
b10 ,
00
b10 +
b101 !
b101 -
14
01
b10000 $
1&
b1011011 (
#920
1"
1H
1G
b110 ,
1?
0D
1A
0K
1C
1J
1>
1F
b1110 +
b0 !
b0 -
04
b10100 '
b1110 %
b1110 *
0&
b1011100 (
#930
19
18
0G
10
1@
0?
0"
11
0<
b11 ,
17
1D
0A
0K
0H
13
1;
0:
0C
0J
1/
06
0>
0F
b1 +
b100 !
b100 -
04
b10001 $
1&
b1011101 (
#940
1"
1H
1G
1?
0D
1A
0K
09
0;
1:
1C
1J
08
16
1>
1F
b110 ,
00
b1111 +
b1 !
b1 -
14
01
b10011 '
b1111 %
b1111 *
0&
b1011110 (
#950
0@
07
1<
0G
0?
0"
0D
0A
0K
0H
09
03
1;
0:
0C
0J
08
0/
06
0>
0F
b0 ,
00
b0 +
b11 !
b11 -
14
01
b10010 $
1&
b1011111 (
#960
13
1.
b11 !
b11 -
14
b11 '
b11 $
b11 #
b11 )
b0 %
b0 *
0&
b1100000 (
#970
1"
1H
1G
1?
1A
1@
17
0D
0K
03
12
0;
1:
1C
1J
18
1/
16
1>
1F
b111 ,
10
b1111 +
b11 !
b11 -
14
01
b100 $
1&
b1100001 (
#980
0G
1@
0?
0"
0<
19
b11 ,
17
1D
0A
0K
0H
1;
0:
0C
0J
06
0>
0F
b1 +
b100 !
b100 -
04
b10 '
b1 %
b1 *
0&
b1100010 (
#990
1"
1H
1G
18
1?
11
b111 ,
10
1<
09
0D
1A
0K
13
02
0;
1:
1C
1J
0/
16
1>
1F
b1110 +
b10 !
b10 -
04
b101 $
1&
b1100011 (
#1000
0G
0?
0"
1D
0A
0K
0H
0<
0C
0J
08
0>
0F
b10 ,
00
b10 +
b101 !
b101 -
14
01
b1 '
b10 %
b10 *
0&
b1100100 (
#1010
1"
1H
1G
1?
0D
1A
0K
19
03
12
1;
0:
1C
1J
18
1/
06
1>
1F
b111 ,
10
b1101 +
b1 !
b1 -
14
01
b110 $
1&
b1100101 (
#1020
0G
b11 ,
0?
0"
1<
09
1D
0A
0K
0H
0;
1:
0C
0J
16
0>
0F
b11 +
b110 !
b110 -
04
b0 '
b11 %
b11 *
0&
b1100110 (
#1030
1"
1H
1G
18
1@
1?
11
10
0<
19
b111 ,
17
0D
1A
0K
13
02
1;
0:
1C
1J
0/
06
1>
1F
b1100 +
b0 !
b0 -
04
b111 $
1&
b1100111 (
#1040
0G
0?
1D
0A
0@
0"
07
0K
0H
1<
09
0J
08
0F
b0 ,
00
b100 +
b111 !
b111 -
14
01
b11111 '
b100 %
b100 *
0&
b1101000 (
#1050
1@
17
1D
1K
03
12
0;
1:
0C
1J
18
1/
16
0>
1F
b11 ,
10
b1011 +
b1111 !
b1111 -
14
01
b1000 $
1&
b1101001 (
#1060
1G
1@
1?
0<
19
b111 ,
17
0D
1A
1K
1;
0:
1C
0J
06
1>
0F
b101 +
b1000 !
b1000 -
04
b11110 '
b101 %
b101 *
0&
b1101010 (
#1070
0G
18
0?
0"
11
b11 ,
10
1<
09
1D
0A
1K
0H
13
02
0;
1:
0C
1J
0/
16
0>
1F
b1010 +
b1110 !
b1110 -
04
b1001 $
1&
b1101011 (
#1080
1G
1?
0D
1A
1K
0<
1C
0J
08
1>
0F
b110 ,
00
b110 +
b1001 !
b1001 -
14
01
b11101 '
b110 %
b110 *
0&
b1101100 (
#1090
0G
0?
0"
1D
0A
1K
0H
19
03
12
1;
0:
0C
1J
18
1/
06
0>
1F
b11 ,
10
b1001 +
b1101 !
b1101 -
14
01
b1010 $
1&
b1101101 (
#1100
1G
b111 ,
1?
1<
09
0D
1A
1K
0;
1:
1C
0J
16
1>
0F
b111 +
b1010 !
b1010 -
04
b11100 '
b111 %
b111 *
0&
b1101110 (
#1110
0G
18
1@
0?
0"
11
10
0<
19
b11 ,
17
1D
0A
1K
0H
13
02
1;
0:
0C
1J
0/
06
0>
1F
b1000 +
b1100 !
b1100 -
04
b1011 $
1&
b1101111 (
#1120
0D
0@
07
1<
09
08
b0 ,
00
b1011 !
b1011 -
14
01
b11011 '
b1000 %
b1000 *
0&
b1110000 (
#1130
1G
1?
1A
1@
17
0D
1K
03
12
0;
1:
1C
0J
18
1/
16
1>
0F
b111 ,
10
b111 +
b1011 !
b1011 -
14
01
b1100 $
1&
b1110001 (
#1140
0G
1@
0?
0"
0<
19
b11 ,
17
1D
0A
1K
0H
1;
0:
0C
1J
06
0>
1F
b1001 +
b1100 !
b1100 -
04
b11010 '
b1001 %
b1001 *
0&
b1110010 (
#1150
1G
18
1?
11
b111 ,
10
1<
09
0D
1A
1K
13
02
0;
1:
1C
0J
0/
16
1>
0F
b110 +
b1010 !
b1010 -
04
b1101 $
1&
b1110011 (
#1160
0G
0?
0"
1D
0A
1K
0H
0<
0C
1J
08
0>
1F
b10 ,
00
b1010 +
b1101 !
b1101 -
14
01
b11001 '
b1010 %
b1010 *
0&
b1110100 (
#1170
1G
1?
0D
1A
1K
19
03
12
1;
0:
1C
0J
18
1/
06
1>
0F
b111 ,
10
b101 +
b1001 !
b1001 -
14
01
b1110 $
1&
b1110101 (
#1180
0G
b11 ,
0?
0"
1<
09
1D
0A
1K
0H
0;
1:
0C
1J
16
0>
1F
b1011 +
b1110 !
b1110 -
04
b11000 '
b1011 %
b1011 *
0&
b1110110 (
#1190
1G
18
1@
1?
11
10
0<
19
b111 ,
17
0D
1A
1K
13
02
1;
0:
1C
0J
0/
06
1>
0F
b100 +
b1000 !
b1000 -
04
b1111 $
1&
b1110111 (
#1200
0G
0?
1D
0A
0@
0"
07
1K
0H
1<
09
1J
08
1F
b0 ,
00
b1100 +
b1111 !
b1111 -
14
01
b10111 '
b1100 %
b1100 *
0&
b1111000 (
#1210
1@
17
1D
0K
03
12
0;
1:
0C
0J
18
1/
16
0>
0F
b11 ,
10
b11 +
b111 !
b111 -
14
01
b10000 $
1&
b1111001 (
#1220
1"
1H
1G
1@
1?
0<
19
b111 ,
17
0D
1A
0K
1;
0:
1C
1J
06
1>
1F
b1101 +
b0 !
b0 -
04
b10110 '
b1101 %
b1101 *
0&
b1111010 (
#1230
0G
18
0?
0"
11
b11 ,
10
1<
09
1D
0A
0K
0H
13
02
0;
1:
0C
0J
0/
16
0>
0F
b10 +
b110 !
b110 -
04
b10001 $
1&
b1111011 (
#1240
1"
1H
1G
1?
0D
1A
0K
0<
1C
1J
08
1>
1F
b110 ,
00
b1110 +
b1 !
b1 -
14
01
b10101 '
b1110 %
b1110 *
0&
b1111100 (
#1250
0G
0?
0"
1D
0A
0K
0H
19
03
12
1;
0:
0C
0J
18
1/
06
0>
0F
b11 ,
10
b1 +
b101 !
b101 -
14
01
b10010 $
1&
b1111101 (
#1260
1"
1H
1G
b111 ,
1?
1<
09
0D
1A
0K
0;
1:
1C
1J
16
1>
1F
b1111 +
b10 !
b10 -
04
b10100 '
b1111 %
b1111 *
0&
b1111110 (
#1270
0G
18
1@
0?
0"
11
10
0<
19
b11 ,
17
1D
0A
0K
0H
13
02
1;
0:
0C
0J
0/
06
0>
0F
b0 +
b100 !
b100 -
04
b10011 $
1&
b1111111 (
#1280
0K
0@
0G
07
0?
09
1D
0A
08
03
0;
1C
b0 ,
00
0.
05
1=
b100 !
b100 -
04
01
b100 '
b100 $
b100 #
b100 )
b0 %
b0 *
0&
b10000000 (
#1290
1@
17
19
1"
18
1H
10
1G
11
0<
1D
b111 ,
1?
0K
13
1;
0C
1B
1J
1/
16
1>
1F
b1111 +
b100 !
b100 -
04
b101 $
1&
b10000001 (
#1300
0@
0G
0"
07
1D
0A
0?
0K
0H
09
0;
1C
0B
0J
08
06
0>
0F
b0 ,
00
b1 +
b101 !
b101 -
14
01
b11 '
b1 %
b1 *
0&
b10000010 (
#1310
1<
1"
1H
0@
1G
07
0D
1?
0K
09
03
1;
0C
1B
1J
08
0/
16
1>
1F
b100 ,
00
b1110 +
b11 !
b11 -
14
01
b110 $
1&
b10000011 (
#1320
0G
0"
1D
b0 ,
0?
0K
0H
1C
0B
0J
0>
0F
b10 +
b110 !
b110 -
04
b10 '
b10 %
b10 *
0&
b10000100 (
